.bzrignore
README.txt
setup.py
buildout/__init__.py
buildout.umask.egg-info/PKG-INFO
buildout.umask.egg-info/SOURCES.txt
buildout.umask.egg-info/dependency_links.txt
buildout.umask.egg-info/entry_points.txt
buildout.umask.egg-info/namespace_packages.txt
buildout.umask.egg-info/not-zip-safe
buildout.umask.egg-info/requires.txt
buildout.umask.egg-info/top_level.txt
buildout/umask/__init__.py
docs/HISTORY.txt