Metadata-Version: 1.0
Name: buildout.umask
Version: 0.5.2
Summary: Use a custom umask when running buildout.
Home-page: https://launchpad.net/buildout.umask
Author: Servilio Afre Puentes
Author-email: afrepues@mcmaster.ca
License: GPL
Platform: UNKNOWN
Classifier: Framework :: Buildout
Classifier: Intended Audience :: Developers
Classifier: Programming Language :: Python
Classifier: Topic :: Software Development :: Build Tools
Classifier: Operating System :: POSIX
